pycommentcleaner/__init__.py
pycommentcleaner/cli.py
pycommentcleaner/core.py
pycommentcleaner-0.1.2.dist-info/licenses/LICENSE
pycommentcleaner-0.1.2.dist-info/METADATA
pycommentcleaner-0.1.2.dist-info/WHEEL
pycommentcleaner-0.1.2.dist-info/entry_points.txt
pycommentcleaner-0.1.2.dist-info/top_level.txt
pycommentcleaner-0.1.2.dist-info/RECORD
