Metadata-Version: 2.4
Name: pycommentcleaner
Version: 0.1.2
Summary: A simple and fast Python utility to remove comments from Python scripts.
Home-page: https://github.com/viekayy/pycommentcleaner.git
Author: Viadishwar
Author-email: viekayy.1234@gmail.com
Keywords: python,comments,cleaner,utility,development
Classifier: Development Status :: 3 - Alpha
Classifier: Intended Audience :: Developers
Classifier: License :: OSI Approved :: MIT License
Classifier: Programming Language :: Python :: 3
Classifier: Programming Language :: Python :: 3.6
Classifier: Programming Language :: Python :: 3.7
Classifier: Programming Language :: Python :: 3.8
Classifier: Programming Language :: Python :: 3.9
Classifier: Programming Language :: Python :: 3.10
Classifier: Topic :: Software Development :: Libraries :: Python Modules
Classifier: Topic :: Utilities
Requires-Python: >=3.6
License-File: LICENSE
Dynamic: author
Dynamic: author-email
Dynamic: classifier
Dynamic: description
Dynamic: description-content-type
Dynamic: home-page
Dynamic: keywords
Dynamic: license-file
Dynamic: requires-python
Dynamic: summary
